datanab/__init__.py
datanab-0.0.2.dist-info/DESCRIPTION.rst
datanab-0.0.2.dist-info/METADATA
datanab-0.0.2.dist-info/RECORD
datanab-0.0.2.dist-info/WHEEL
datanab-0.0.2.dist-info/metadata.json
datanab-0.0.2.dist-info/top_level.txt
