Metadata-Version: 2.0
Name: datanab
Version: 0.0.2
Summary: A Python wrapper around the datanab API
Home-page: https://github.com/jmfernandes/datanab
Author: Josh Fernandes
Author-email: joshfernandes@mac.com
License: MIT
Keywords: datanab
Platform: UNKNOWN
Requires: requests
Requires-Python: >=3
Requires-Dist: requests
